qiskit_optimization/VERSION.txt
qiskit_optimization/__init__.py
qiskit_optimization/exceptions.py
qiskit_optimization/infinity.py
qiskit_optimization/optionals.py
qiskit_optimization/py.typed
qiskit_optimization/version.py
qiskit_optimization/algorithms/__init__.py
qiskit_optimization/algorithms/admm_optimizer.py
qiskit_optimization/algorithms/cobyla_optimizer.py
qiskit_optimization/algorithms/cplex_optimizer.py
qiskit_optimization/algorithms/goemans_williamson_optimizer.py
qiskit_optimization/algorithms/grover_optimizer.py
qiskit_optimization/algorithms/gurobi_optimizer.py
qiskit_optimization/algorithms/minimum_eigen_optimizer.py
qiskit_optimization/algorithms/multistart_optimizer.py
qiskit_optimization/algorithms/optimization_algorithm.py
qiskit_optimization/algorithms/recursive_minimum_eigen_optimizer.py
qiskit_optimization/algorithms/scipy_milp_optimizer.py
qiskit_optimization/algorithms/slsqp_optimizer.py
qiskit_optimization/algorithms/warm_start_qaoa_optimizer.py
qiskit_optimization/algorithms/qrao/__init__.py
qiskit_optimization/algorithms/qrao/encoding_commutation_verifier.py
qiskit_optimization/algorithms/qrao/magic_rounding.py
qiskit_optimization/algorithms/qrao/quantum_random_access_encoding.py
qiskit_optimization/algorithms/qrao/quantum_random_access_optimizer.py
qiskit_optimization/algorithms/qrao/rounding_common.py
qiskit_optimization/algorithms/qrao/semideterministic_rounding.py
qiskit_optimization/applications/__init__.py
qiskit_optimization/applications/bin_packing.py
qiskit_optimization/applications/clique.py
qiskit_optimization/applications/exact_cover.py
qiskit_optimization/applications/graph_optimization_application.py
qiskit_optimization/applications/graph_partition.py
qiskit_optimization/applications/knapsack.py
qiskit_optimization/applications/max_cut.py
qiskit_optimization/applications/number_partition.py
qiskit_optimization/applications/optimization_application.py
qiskit_optimization/applications/set_packing.py
qiskit_optimization-0.6.0.dist-info/LICENSE.txt
qiskit_optimization-0.6.0.dist-info/METADATA
qiskit_optimization-0.6.0.dist-info/WHEEL
qiskit_optimization-0.6.0.dist-info/top_level.txt
qiskit_optimization-0.6.0.dist-info/RECORD
