Metadata-Version: 2.1
Name: qiskit-optimization
Version: 0.6.0
Summary: Qiskit Optimization: A library for optimization applications using quantum computing
Home-page: https://github.com/qiskit-community/qiskit-optimization
Author: Qiskit Optimization Development Team
Author-email: hello@qiskit.org
License: Apache-2.0
Project-URL: Bug Tracker, https://github.com/qiskit-community/qiskit-optimization/issues
Project-URL: Documentation, https://qiskit.org/ecosystem/optimization/
Project-URL: Source Code, https://github.com/qiskit-community/qiskit-optimization
Keywords: qiskit sdk quantum optimization
Classifier: Environment :: Console
Classifier: License :: OSI Approved :: Apache Software License
Classifier: Intended Audience :: Developers
Classifier: Intended Audience :: Science/Research
Classifier: Operating System :: Microsoft :: Windows
Classifier: Operating System :: MacOS
Classifier: Operating System :: POSIX :: Linux
Classifier: Programming Language :: Python :: 3 :: Only
Classifier: Programming Language :: Python :: 3.8
Classifier: Programming Language :: Python :: 3.9
Classifier: Programming Language :: Python :: 3.10
Classifier: Programming Language :: Python :: 3.11
Classifier: Topic :: Scientific/Engineering
Requires-Python: >=3.8
License-File: LICENSE.txt
Requires-Dist: qiskit>=0.44
Requires-Dist: qiskit-algorithms>=0.2.0
Requires-Dist: scipy>=1.9.0
Requires-Dist: numpy>=1.17
Requires-Dist: docplex!=2.24.231,>=2.21.207
Requires-Dist: setuptools>=40.1.0
Requires-Dist: networkx>=2.6.3
Provides-Extra: cplex
Requires-Dist: cplex; extra == "cplex"
Provides-Extra: cvx
Requires-Dist: cvxpy; extra == "cvx"
Provides-Extra: matplotlib
Requires-Dist: matplotlib; extra == "matplotlib"
Provides-Extra: gurobi
Requires-Dist: gurobipy; extra == "gurobi"
